pyramid_urireferencer/__init__.py
pyramid_urireferencer/models.py
pyramid_urireferencer/protected_resources.py
pyramid_urireferencer/referencer.py
pyramid_urireferencer/renderers.py
pyramid_urireferencer/views.py
pyramid_urireferencer-0.8.0.dist-info/LICENSE
pyramid_urireferencer-0.8.0.dist-info/METADATA
pyramid_urireferencer-0.8.0.dist-info/WHEEL
pyramid_urireferencer-0.8.0.dist-info/top_level.txt
pyramid_urireferencer-0.8.0.dist-info/RECORD
