Metadata-Version: 2.1
Name: pyramid-urireferencer
Version: 0.8.0
Summary: A pyramid plugin to handle referencing external URIs.
Home-page: https://github.com/OnroerendErfgoed/pyramid_urireferencer
Author: Flanders Heritage Agency
Author-email: ict@onroerenderfgoed.be
License: UNKNOWN
Keywords: web wsgi pyramid uri REST references
Platform: UNKNOWN
Classifier: License :: OSI Approved :: MIT License
Classifier: Intended Audience :: Developers
Classifier: Framework :: Pyramid
Classifier: Topic :: Internet :: WWW/HTTP
Classifier: Topic :: Internet :: WWW/HTTP :: WSGI :: Application
Classifier: Programming Language :: Python
Classifier: Programming Language :: Python :: 2.7
Classifier: Programming Language :: Python :: 3.3
Classifier: Programming Language :: Python :: 3.4
Classifier: Programming Language :: Python :: 3.5
Requires-Dist: pyramid
Requires-Dist: requests
Requires-Dist: six
